[
  {
    "childFolders": [
      {
        "fileType": 0,
        "fileName": "내 문서",
        "childFolders": []
      },
      {
        "fileType": 12,
        "fileName": "Blackout",
        "childFolders": []
      },
      {
        "fileType": 13,
        "fileName": "Blobfish",
        "childFolders": []
      },
      {
        "fileType": 14,
        "fileName": "GateGuadian",
        "childFolders": []
      },
      {
        "fileType": 15,
        "fileName": "MagicalGirls",
        "childFolders": []
      },
      {
        "fileType": 8,
        "fileName": "오싹오싹 밴드부",
        "childFolders": []
      },
      {
        "fileType": 16,
        "fileName": "NegativeNarrative",
        "childFolders": []
      },
      {
        "fileType": 17,
        "fileName": "RescueUnion",
        "childFolders": []
      },
      {
        "fileType": 18,
        "fileName": "The t",
        "childFolders": []
      },
      {
        "fileType": 9,
        "fileName": "THE LEGEND COWBOY",
        "childFolders": []
      },
      {
        "fileType": 10,
        "fileName": "THE HOSPITAL",
        "childFolders": []
      }
    ]
  }
]